YeelightPool/YeelightBulb.py
YeelightPool/YeelightConfig.py
YeelightPool/YeelightLamp.py
YeelightPool/__init__.py
YeelightPool/const.py
YeelightPool/example.py
yeelightpool-0.1.1.dist-info/WHEEL
yeelightpool-0.1.1.dist-info/METADATA
yeelightpool-0.1.1.dist-info/RECORD
