Metadata-Version: 2.1
Name: YeelightPool
Version: 0.1.1
Summary: A package to integrate Yeelight bulbs and lamps with MQTT Broker.
Author-email: ftcid <fernando.tor.c@gmail.com>
Requires-Python: >=3.7
Classifier: Programming Language :: Python :: 3
Classifier: License :: OSI Approved :: Apache Software License
Classifier: Operating System :: OS Independent
Requires-Dist: paho-mqtt>=1.5.1
Requires-Dist: yeelight>=0.6.2
Project-URL: Homepage, https://github.com/ftcid/yeelightpool
Project-URL: Issues, https://github.com/ftcid/yeelightpool
